[
    {
        "Name": "Melana BO",
        "District": "BHAVNAGAR",
        "State": "GUJARAT",
        "Region": "Rajkot Region",
        "Division": "Bhavnagar Division",
        "Country": "India"
    },
    {
        "Name": "Zinzavadar Nana BO",
        "District": "BOTAD",
        "State": "GUJARAT",
        "Region": "Rajkot Region",
        "Division": "Bhavnagar Division",
        "Country": "India"
    },
    {
        "Name": "Dared BO",
        "District": "BHAVNAGAR",
        "State": "GUJARAT",
        "Region": "Rajkot Region",
        "Division": "Bhavnagar Division",
        "Country": "India"
    },
    {
        "Name": "Lakheni BO",
        "District": "BOTAD",
        "State": "GUJARAT",
        "Region": "Rajkot Region",
        "Division": "Bhavnagar Division",
        "Country": "India"
    },
    {
        "Name": "Pati BO",
        "District": "BOTAD",
        "State": "GUJARAT",
        "Region": "Rajkot Region",
        "Division": "Bhavnagar Division",
        "Country": "India"
    },
    {
        "Name": "Shiyanagar BO",
        "District": "BOTAD",
        "State": "GUJARAT",
        "Region": "Rajkot Region",
        "Division": "Bhavnagar Division",
        "Country": "India"
    },
    {
        "Name": "Rohishala BO",
        "District": "BOTAD",
        "State": "GUJARAT",
        "Region": "Rajkot Region",
        "Division": "Bhavnagar Division",
        "Country": "India"
    },
    {
        "Name": "Ningala SO",
        "District": "BOTAD",
        "State": "GUJARAT",
        "Region": "Rajkot Region",
        "Division": "Bhavnagar Division",
        "Country": "India"
    },
    {
        "Name": "Zinza Vadar Mota BO",
        "District": "BOTAD",
        "State": "GUJARAT",
        "Region": "Rajkot Region",
        "Division": "Bhavnagar Division",
        "Country": "India"
    }
]