[
    {
        "Name": "Patna Buzurg B.O",
        "District": "SAGAR",
        "State": "MADHYA PRADESH",
        "Region": "Jabalpur Region",
        "Division": "Sagar Division",
        "Country": "India"
    },
    {
        "Name": "Tinsi B.O",
        "District": "SAGAR",
        "State": "MADHYA PRADESH",
        "Region": "Jabalpur Region",
        "Division": "Sagar Division",
        "Country": "India"
    },
    {
        "Name": "Dhana S.O",
        "District": "SAGAR",
        "State": "MADHYA PRADESH",
        "Region": "Jabalpur Region",
        "Division": "Sagar Division",
        "Country": "India"
    },
    {
        "Name": "Bamori Bika B.O",
        "District": "SAGAR",
        "State": "MADHYA PRADESH",
        "Region": "Jabalpur Region",
        "Division": "Sagar Division",
        "Country": "India"
    },
    {
        "Name": "Hilgan B.O",
        "District": "SAGAR",
        "State": "MADHYA PRADESH",
        "Region": "Jabalpur Region",
        "Division": "Sagar Division",
        "Country": "India"
    },
    {
        "Name": "Baroda Rehli B.O",
        "District": "SAGAR",
        "State": "MADHYA PRADESH",
        "Region": "Jabalpur Region",
        "Division": "Sagar Division",
        "Country": "India"
    }
]