[
    {
        "Name": "Chhanta B.O",
        "District": "DINDORI",
        "State": "MADHYA PRADESH",
        "Region": "Jabalpur Region",
        "Division": "Mandla Division",
        "Country": "India"
    },
    {
        "Name": "Deori Mal B.O",
        "District": "DINDORI",
        "State": "MADHYA PRADESH",
        "Region": "Jabalpur Region",
        "Division": "Mandla Division",
        "Country": "India"
    },
    {
        "Name": "Kisalpuri B.O",
        "District": "DINDORI",
        "State": "MADHYA PRADESH",
        "Region": "Jabalpur Region",
        "Division": "Mandla Division",
        "Country": "India"
    },
    {
        "Name": "Dhanwasi B.O",
        "District": "DINDORI",
        "State": "MADHYA PRADESH",
        "Region": "Jabalpur Region",
        "Division": "Mandla Division",
        "Country": "India"
    },
    {
        "Name": "Bhaiswahi B.O",
        "District": "DINDORI",
        "State": "MADHYA PRADESH",
        "Region": "Jabalpur Region",
        "Division": "Mandla Division",
        "Country": "India"
    },
    {
        "Name": "Newsapondi B.O",
        "District": "DINDORI",
        "State": "MADHYA PRADESH",
        "Region": "Jabalpur Region",
        "Division": "Mandla Division",
        "Country": "India"
    },
    {
        "Name": "Raypura B.O",
        "District": "DINDORI",
        "State": "MADHYA PRADESH",
        "Region": "Jabalpur Region",
        "Division": "Mandla Division",
        "Country": "India"
    },
    {
        "Name": "Dindori S.O (Dindori)",
        "District": "DINDORI",
        "State": "MADHYA PRADESH",
        "Region": "Jabalpur Region",
        "Division": "Mandla Division",
        "Country": "India"
    },
    {
        "Name": "Kukarramath B.O",
        "District": "DINDORI",
        "State": "MADHYA PRADESH",
        "Region": "Jabalpur Region",
        "Division": "Mandla Division",
        "Country": "India"
    },
    {
        "Name": "Madiyaras B.O",
        "District": "DINDORI",
        "State": "MADHYA PRADESH",
        "Region": "Jabalpur Region",
        "Division": "Mandla Division",
        "Country": "India"
    },
    {
        "Name": "Padariya Kala B.O",
        "District": "DINDORI",
        "State": "MADHYA PRADESH",
        "Region": "Jabalpur Region",
        "Division": "Mandla Division",
        "Country": "India"
    },
    {
        "Name": "Sakka B.O",
        "District": "DINDORI",
        "State": "MADHYA PRADESH",
        "Region": "Jabalpur Region",
        "Division": "Mandla Division",
        "Country": "India"
    },
    {
        "Name": "Simariya B.O",
        "District": "DINDORI",
        "State": "MADHYA PRADESH",
        "Region": "Jabalpur Region",
        "Division": "Mandla Division",
        "Country": "India"
    },
    {
        "Name": "Amarpur B.O",
        "District": "DINDORI",
        "State": "MADHYA PRADESH",
        "Region": "Jabalpur Region",
        "Division": "Mandla Division",
        "Country": "India"
    },
    {
        "Name": "Kamrasoda B.O",
        "District": "DINDORI",
        "State": "MADHYA PRADESH",
        "Region": "Jabalpur Region",
        "Division": "Mandla Division",
        "Country": "India"
    },
    {
        "Name": "Mudki B.O",
        "District": "DINDORI",
        "State": "MADHYA PRADESH",
        "Region": "Jabalpur Region",
        "Division": "Mandla Division",
        "Country": "India"
    }
]