[
    {
        "Name": "Kalhadi B.O",
        "District": "NIZAMABAD",
        "State": "TELANGANA",
        "Region": "Hyderabad Region",
        "Division": "Nizamabad Division",
        "Country": "India"
    },
    {
        "Name": "Ramchandrapalli B.O",
        "District": "NIZAMABAD",
        "State": "TELANGANA",
        "Region": "Hyderabad Region",
        "Division": "Nizamabad Division",
        "Country": "India"
    },
    {
        "Name": "Andhranagar B.O",
        "District": "NIZAMABAD",
        "State": "TELANGANA",
        "Region": "Hyderabad Region",
        "Division": "Nizamabad Division",
        "Country": "India"
    },
    {
        "Name": "Gutpa B.O",
        "District": "NIZAMABAD",
        "State": "TELANGANA",
        "Region": "Hyderabad Region",
        "Division": "Nizamabad Division",
        "Country": "India"
    },
    {
        "Name": "Makloor S.O",
        "District": "NIZAMABAD",
        "State": "TELANGANA",
        "Region": "Hyderabad Region",
        "Division": "Nizamabad Division",
        "Country": "India"
    },
    {
        "Name": "MADHAPUR B.O",
        "District": "NIZAMABAD",
        "State": "TELANGANA",
        "Region": "Hyderabad Region",
        "Division": "Nizamabad Division",
        "Country": "India"
    },
    {
        "Name": "Mullangi B.O",
        "District": "NIZAMABAD",
        "State": "TELANGANA",
        "Region": "Hyderabad Region",
        "Division": "Nizamabad Division",
        "Country": "India"
    },
    {
        "Name": "Deekampalli B.O",
        "District": "NIZAMABAD",
        "State": "TELANGANA",
        "Region": "Hyderabad Region",
        "Division": "Nizamabad Division",
        "Country": "India"
    },
    {
        "Name": "YELMAL B.O",
        "District": "NIZAMABAD",
        "State": "TELANGANA",
        "Region": "Hyderabad Region",
        "Division": "Nizamabad Division",
        "Country": "India"
    }
]