[
    {
        "Name": "Chinnahyti B.O",
        "District": "KURNOOL",
        "State": "ANDHRA PRADESH",
        "Region": "Kurnool Region",
        "Division": "Kurnool Division",
        "Country": "India"
    },
    {
        "Name": "Honnur B.O",
        "District": "KURNOOL",
        "State": "ANDHRA PRADESH",
        "Region": "Kurnool Region",
        "Division": "Kurnool Division",
        "Country": "India"
    },
    {
        "Name": "Marlamadiki B.O",
        "District": "KURNOOL",
        "State": "ANDHRA PRADESH",
        "Region": "Kurnool Region",
        "Division": "Kurnool Division",
        "Country": "India"
    },
    {
        "Name": "Sammatageri B.O",
        "District": "KURNOOL",
        "State": "ANDHRA PRADESH",
        "Region": "Kurnool Region",
        "Division": "Kurnool Division",
        "Country": "India"
    },
    {
        "Name": "Virupapuram B.O",
        "District": "KURNOOL",
        "State": "ANDHRA PRADESH",
        "Region": "Kurnool Region",
        "Division": "Kurnool Division",
        "Country": "India"
    },
    {
        "Name": "Holalagondi S.O",
        "District": "KURNOOL",
        "State": "ANDHRA PRADESH",
        "Region": "Kurnool Region",
        "Division": "Kurnool Division",
        "Country": "India"
    },
    {
        "Name": "Kogilathota B.O",
        "District": "KURNOOL",
        "State": "ANDHRA PRADESH",
        "Region": "Kurnool Region",
        "Division": "Kurnool Division",
        "Country": "India"
    }
]