[
    {
        "Name": "Nallabothulavaripalem B.O",
        "District": "PRAKASAM",
        "State": "ANDHRA PRADESH",
        "Region": "Vijayawada Region",
        "Division": "Markapur  Division",
        "Country": "India"
    },
    {
        "Name": "Thummedalapadu B.O",
        "District": "PRAKASAM",
        "State": "ANDHRA PRADESH",
        "Region": "Vijayawada Region",
        "Division": "Markapur  Division",
        "Country": "India"
    },
    {
        "Name": "Donakonda R.S. S.O",
        "District": "PRAKASAM",
        "State": "ANDHRA PRADESH",
        "Region": "Vijayawada Region",
        "Division": "Markapur  Division",
        "Country": "India"
    },
    {
        "Name": "Chandavaram B.O",
        "District": "PRAKASAM",
        "State": "ANDHRA PRADESH",
        "Region": "Vijayawada Region",
        "Division": "Markapur  Division",
        "Country": "India"
    },
    {
        "Name": "Rudrasamudram B.O",
        "District": "PRAKASAM",
        "State": "ANDHRA PRADESH",
        "Region": "Vijayawada Region",
        "Division": "Markapur  Division",
        "Country": "India"
    },
    {
        "Name": "Gudipadu B.O",
        "District": "PRAKASAM",
        "State": "ANDHRA PRADESH",
        "Region": "Vijayawada Region",
        "Division": "Markapur  Division",
        "Country": "India"
    },
    {
        "Name": "Lakshmipuram B.O",
        "District": "PRAKASAM",
        "State": "ANDHRA PRADESH",
        "Region": "Vijayawada Region",
        "Division": "Markapur  Division",
        "Country": "India"
    },
    {
        "Name": "Polepalle B.O",
        "District": "PRAKASAM",
        "State": "ANDHRA PRADESH",
        "Region": "Vijayawada Region",
        "Division": "Markapur  Division",
        "Country": "India"
    },
    {
        "Name": "Ramapuram B.O",
        "District": "PRAKASAM",
        "State": "ANDHRA PRADESH",
        "Region": "Vijayawada Region",
        "Division": "Markapur  Division",
        "Country": "India"
    },
    {
        "Name": "Aravallipadu B.O",
        "District": "PRAKASAM",
        "State": "ANDHRA PRADESH",
        "Region": "Vijayawada Region",
        "Division": "Markapur  Division",
        "Country": "India"
    },
    {
        "Name": "Vaddipadu B.O",
        "District": "PRAKASAM",
        "State": "ANDHRA PRADESH",
        "Region": "Vijayawada Region",
        "Division": "Markapur  Division",
        "Country": "India"
    },
    {
        "Name": "Vekatapuram B.O",
        "District": "PRAKASAM",
        "State": "ANDHRA PRADESH",
        "Region": "Vijayawada Region",
        "Division": "Markapur  Division",
        "Country": "India"
    },
    {
        "Name": "Badapuram B.O",
        "District": "PRAKASAM",
        "State": "ANDHRA PRADESH",
        "Region": "Vijayawada Region",
        "Division": "Markapur  Division",
        "Country": "India"
    },
    {
        "Name": "Gangadevipalle B.O",
        "District": "PRAKASAM",
        "State": "ANDHRA PRADESH",
        "Region": "Vijayawada Region",
        "Division": "Markapur  Division",
        "Country": "India"
    },
    {
        "Name": "Indlacheruvu B.O",
        "District": "PRAKASAM",
        "State": "ANDHRA PRADESH",
        "Region": "Vijayawada Region",
        "Division": "Markapur  Division",
        "Country": "India"
    }
]