[
    {
        "Name": "Madabhavi B.O",
        "District": "BAGALKOT",
        "State": "KARNATAKA",
        "Region": "North Karnataka Region",
        "Division": "Bagalkot Division",
        "Country": "India"
    },
    {
        "Name": "Sameerwadi S.O",
        "District": "BAGALKOT",
        "State": "KARNATAKA",
        "Region": "North Karnataka Region",
        "Division": "Bagalkot Division",
        "Country": "India"
    },
    {
        "Name": "Saidapur B.O",
        "District": "BAGALKOT",
        "State": "KARNATAKA",
        "Region": "North Karnataka Region",
        "Division": "Bagalkot Division",
        "Country": "India"
    },
    {
        "Name": "Marapur B.O",
        "District": "BAGALKOT",
        "State": "KARNATAKA",
        "Region": "North Karnataka Region",
        "Division": "Bagalkot Division",
        "Country": "India"
    }
]