[
    {
        "Name": "Kalacheri B.O",
        "District": "THIRUVARUR",
        "State": "TAMIL NADU",
        "Region": "Central Region Trichirapalli",
        "Division": "Thanjavur Division",
        "Country": "India"
    },
    {
        "Name": "Kilapattu B.O",
        "District": "THIRUVARUR",
        "State": "TAMIL NADU",
        "Region": "Central Region Trichirapalli",
        "Division": "Thanjavur Division",
        "Country": "India"
    },
    {
        "Name": "Rayapuram B.O",
        "District": "THIRUVARUR",
        "State": "TAMIL NADU",
        "Region": "Central Region Trichirapalli",
        "Division": "Thanjavur Division",
        "Country": "India"
    },
    {
        "Name": "Devangudi B.O",
        "District": "THIRUVARUR",
        "State": "TAMIL NADU",
        "Region": "Central Region Trichirapalli",
        "Division": "Thanjavur Division",
        "Country": "India"
    },
    {
        "Name": "Kalanjimodu B.O",
        "District": "THIRUVARUR",
        "State": "TAMIL NADU",
        "Region": "Central Region Trichirapalli",
        "Division": "Thanjavur Division",
        "Country": "India"
    },
    {
        "Name": "Melalavandaseri B.O",
        "District": "THIRUVARUR",
        "State": "TAMIL NADU",
        "Region": "Central Region Trichirapalli",
        "Division": "Thanjavur Division",
        "Country": "India"
    },
    {
        "Name": "Puvanur S.O",
        "District": "THIRUVARUR",
        "State": "TAMIL NADU",
        "Region": "Central Region Trichirapalli",
        "Division": "Thanjavur Division",
        "Country": "India"
    },
    {
        "Name": "Rajappayyanchavadi B.O",
        "District": "THIRUVARUR",
        "State": "TAMIL NADU",
        "Region": "Central Region Trichirapalli",
        "Division": "Thanjavur Division",
        "Country": "India"
    }
]