[
    {
        "Name": "Pallividai B.O",
        "District": "TIRUCHIRAPPALLI",
        "State": "TAMIL NADU",
        "Region": "Central Region Trichirapalli",
        "Division": "Srirangam Division",
        "Country": "India"
    },
    {
        "Name": "Devimangalam B.O",
        "District": "TIRUCHIRAPPALLI",
        "State": "TAMIL NADU",
        "Region": "Central Region Trichirapalli",
        "Division": "Srirangam Division",
        "Country": "India"
    },
    {
        "Name": "Marudur B.O",
        "District": "TIRUCHIRAPPALLI",
        "State": "TAMIL NADU",
        "Region": "Central Region Trichirapalli",
        "Division": "Srirangam Division",
        "Country": "India"
    },
    {
        "Name": "Samayapuram S.O",
        "District": "TIRUCHIRAPPALLI",
        "State": "TAMIL NADU",
        "Region": "Central Region Trichirapalli",
        "Division": "Srirangam Division",
        "Country": "India"
    }
]