[
    {
        "Name": "Sivakasi HO",
        "District": "VIRUDHUNAGAR",
        "State": "TAMIL NADU",
        "Region": "Southern Region Madurai",
        "Division": "Virudhunagar Division",
        "Country": "India"
    },
    {
        "Name": "Sivakasi Bazzar SO",
        "District": "VIRUDHUNAGAR",
        "State": "TAMIL NADU",
        "Region": "Southern Region Madurai",
        "Division": "Virudhunagar Division",
        "Country": "India"
    },
    {
        "Name": "Sivakasi R S SO",
        "District": "VIRUDHUNAGAR",
        "State": "TAMIL NADU",
        "Region": "Southern Region Madurai",
        "Division": "Virudhunagar Division",
        "Country": "India"
    }
]