[
    {
        "Name": "Basilapir B.O",
        "District": "MAYURBHANJ",
        "State": "ODISHA",
        "Region": "Bhubaneswar HQ Region",
        "Division": "Rairangpur Division",
        "Country": "India"
    },
    {
        "Name": "Jhipabandh B.O",
        "District": "MAYURBHANJ",
        "State": "ODISHA",
        "Region": "Bhubaneswar HQ Region",
        "Division": "Rairangpur Division",
        "Country": "India"
    },
    {
        "Name": "Kathbharia B.O",
        "District": "MAYURBHANJ",
        "State": "ODISHA",
        "Region": "Bhubaneswar HQ Region",
        "Division": "Rairangpur Division",
        "Country": "India"
    },
    {
        "Name": "Dova B.O",
        "District": "MAYURBHANJ",
        "State": "ODISHA",
        "Region": "Bhubaneswar HQ Region",
        "Division": "Rairangpur Division",
        "Country": "India"
    },
    {
        "Name": "Padhia B.O",
        "District": "MAYURBHANJ",
        "State": "ODISHA",
        "Region": "Bhubaneswar HQ Region",
        "Division": "Rairangpur Division",
        "Country": "India"
    },
    {
        "Name": "Badampahar S.O",
        "District": "MAYURBHANJ",
        "State": "ODISHA",
        "Region": "Bhubaneswar HQ Region",
        "Division": "Rairangpur Division",
        "Country": "India"
    },
    {
        "Name": "Jorda B.O",
        "District": "MAYURBHANJ",
        "State": "ODISHA",
        "Region": "Bhubaneswar HQ Region",
        "Division": "Rairangpur Division",
        "Country": "India"
    },
    {
        "Name": "Talakpokhari B.O",
        "District": "MAYURBHANJ",
        "State": "ODISHA",
        "Region": "Bhubaneswar HQ Region",
        "Division": "Rairangpur Division",
        "Country": "India"
    }
]