[
    {
        "Name": "Deithor B.O",
        "District": "KARBI ANGLONG",
        "State": "ASSAM",
        "Region": "Dibrugarh Region",
        "Division": "Sibsagar Division",
        "Country": "India"
    },
    {
        "Name": "Golaibasti B.O",
        "District": "KARBI ANGLONG",
        "State": "ASSAM",
        "Region": "Dibrugarh Region",
        "Division": "Nagaon Division",
        "Country": "India"
    },
    {
        "Name": "Karagaon B.O",
        "District": "KARBI ANGLONG",
        "State": "ASSAM",
        "Region": "Dibrugarh Region",
        "Division": "Nagaon Division",
        "Country": "India"
    },
    {
        "Name": "Kuligaon B.O",
        "District": "KARBI ANGLONG",
        "State": "ASSAM",
        "Region": "Dibrugarh Region",
        "Division": "Nagaon Division",
        "Country": "India"
    },
    {
        "Name": "Sarihajan B.O",
        "District": "KARBI ANGLONG",
        "State": "ASSAM",
        "Region": "Dibrugarh Region",
        "Division": "Nagaon Division",
        "Country": "India"
    },
    {
        "Name": "Khatkhati B.O",
        "District": "KARBI ANGLONG",
        "State": "ASSAM",
        "Region": "Dibrugarh Region",
        "Division": "Nagaon Division",
        "Country": "India"
    },
    {
        "Name": "Bokajan S.O",
        "District": "KARBI ANGLONG",
        "State": "ASSAM",
        "Region": "Dibrugarh Region",
        "Division": "Nagaon Division",
        "Country": "India"
    },
    {
        "Name": "Dillai Parbat B.O",
        "District": "KARBI ANGLONG",
        "State": "ASSAM",
        "Region": "Dibrugarh Region",
        "Division": "Nagaon Division",
        "Country": "India"
    },
    {
        "Name": "Gautambasti B.O",
        "District": "KARBI ANGLONG",
        "State": "ASSAM",
        "Region": "Dibrugarh Region",
        "Division": "Nagaon Division",
        "Country": "India"
    },
    {
        "Name": "Hidipi B.O",
        "District": "KARBI ANGLONG",
        "State": "ASSAM",
        "Region": "Dibrugarh Region",
        "Division": "Nagaon Division",
        "Country": "India"
    },
    {
        "Name": "Kailajan B.O",
        "District": "KARBI ANGLONG",
        "State": "ASSAM",
        "Region": "Dibrugarh Region",
        "Division": "Nagaon Division",
        "Country": "India"
    },
    {
        "Name": "Laharijan B.O",
        "District": "KARBI ANGLONG",
        "State": "ASSAM",
        "Region": "Dibrugarh Region",
        "Division": "Nagaon Division",
        "Country": "India"
    },
    {
        "Name": "Dillai B.O",
        "District": "KARBI ANGLONG",
        "State": "ASSAM",
        "Region": "Dibrugarh Region",
        "Division": "Nagaon Division",
        "Country": "India"
    },
    {
        "Name": "Morakordoiguri B.O",
        "District": "KARBI ANGLONG",
        "State": "ASSAM",
        "Region": "Dibrugarh Region",
        "Division": "Nagaon Division",
        "Country": "India"
    }
]