[
    {
        "Name": "Dollygunj B.O",
        "District": "SOUTH ANDAMANS",
        "State": "ANDAMAN AND NICOBAR ISLANDS",
        "Region": "DivReportingCircle",
        "Division": "A - N Islands Division",
        "Country": "India"
    },
    {
        "Name": "Ograbanj B.O",
        "District": "SOUTH ANDAMANS",
        "State": "ANDAMAN AND NICOBAR ISLANDS",
        "Region": "DivReportingCircle",
        "Division": "A - N Islands Division",
        "Country": "India"
    },
    {
        "Name": "Minnie Bay S.O",
        "District": "SOUTH ANDAMANS",
        "State": "ANDAMAN AND NICOBAR ISLANDS",
        "Region": "DivReportingCircle",
        "Division": "A - N Islands Division",
        "Country": "India"
    },
    {
        "Name": "Brijgunj B.O",
        "District": "SOUTH ANDAMANS",
        "State": "ANDAMAN AND NICOBAR ISLANDS",
        "Region": "DivReportingCircle",
        "Division": "A - N Islands Division",
        "Country": "India"
    },
    {
        "Name": "Guptapara B.O",
        "District": "SOUTH ANDAMANS",
        "State": "ANDAMAN AND NICOBAR ISLANDS",
        "Region": "DivReportingCircle",
        "Division": "A - N Islands Division",
        "Country": "India"
    },
    {
        "Name": "Wandoor B.O",
        "District": "SOUTH ANDAMANS",
        "State": "ANDAMAN AND NICOBAR ISLANDS",
        "Region": "DivReportingCircle",
        "Division": "A - N Islands Division",
        "Country": "India"
    },
    {
        "Name": "Herbertabad B.O",
        "District": "SOUTH ANDAMANS",
        "State": "ANDAMAN AND NICOBAR ISLANDS",
        "Region": "DivReportingCircle",
        "Division": "A - N Islands Division",
        "Country": "India"
    },
    {
        "Name": "Junglighat S.O",
        "District": "SOUTH ANDAMANS",
        "State": "ANDAMAN AND NICOBAR ISLANDS",
        "Region": "DivReportingCircle",
        "Division": "A - N Islands Division",
        "Country": "India"
    },
    {
        "Name": "Chouldari B.O",
        "District": "SOUTH ANDAMANS",
        "State": "ANDAMAN AND NICOBAR ISLANDS",
        "Region": "DivReportingCircle",
        "Division": "A - N Islands Division",
        "Country": "India"
    },
    {
        "Name": "Tushnabad B.O",
        "District": "SOUTH ANDAMANS",
        "State": "ANDAMAN AND NICOBAR ISLANDS",
        "Region": "DivReportingCircle",
        "Division": "A - N Islands Division",
        "Country": "India"
    }
]