[
    {
        "Name": "Malkavathe B.O",
        "District": "SOLAPUR",
        "State": "MAHARASHTRA",
        "Region": "Pune Region",
        "Division": "Solapur Division",
        "Country": "India"
    },
    {
        "Name": "Bhandar Kavathe B.O",
        "District": "SOLAPUR",
        "State": "MAHARASHTRA",
        "Region": "Pune Region",
        "Division": "Solapur Division",
        "Country": "India"
    },
    {
        "Name": "Mandrup S.O",
        "District": "SOLAPUR",
        "State": "MAHARASHTRA",
        "Region": "Pune Region",
        "Division": "Solapur Division",
        "Country": "India"
    },
    {
        "Name": "Kandalgaon B.O",
        "District": "SOLAPUR",
        "State": "MAHARASHTRA",
        "Region": "Pune Region",
        "Division": "Solapur Division",
        "Country": "India"
    },
    {
        "Name": "Auj B.O",
        "District": "SOLAPUR",
        "State": "MAHARASHTRA",
        "Region": "Pune Region",
        "Division": "Solapur Division",
        "Country": "India"
    },
    {
        "Name": "Kusur B.O",
        "District": "SOLAPUR",
        "State": "MAHARASHTRA",
        "Region": "Pune Region",
        "Division": "Solapur Division",
        "Country": "India"
    },
    {
        "Name": "Gunjegaon B.O",
        "District": "SOLAPUR",
        "State": "MAHARASHTRA",
        "Region": "Pune Region",
        "Division": "Solapur Division",
        "Country": "India"
    },
    {
        "Name": "Antroli B.O",
        "District": "SOLAPUR",
        "State": "MAHARASHTRA",
        "Region": "Pune Region",
        "Division": "Solapur Division",
        "Country": "India"
    },
    {
        "Name": "Nimbargi B.O",
        "District": "SOLAPUR",
        "State": "MAHARASHTRA",
        "Region": "Pune Region",
        "Division": "Solapur Division",
        "Country": "India"
    },
    {
        "Name": "Vinchur B.O",
        "District": "SOLAPUR",
        "State": "MAHARASHTRA",
        "Region": "Pune Region",
        "Division": "Solapur Division",
        "Country": "India"
    },
    {
        "Name": "Wangi B.O",
        "District": "SOLAPUR",
        "State": "MAHARASHTRA",
        "Region": "Pune Region",
        "Division": "Solapur Division",
        "Country": "India"
    }
]