[
    {
        "Name": "Digras B.O",
        "District": "NANDED",
        "State": "MAHARASHTRA",
        "Region": "Regional Office Aurangabad",
        "Division": "Nanded Division",
        "Country": "India"
    },
    {
        "Name": "Hadoli B.O",
        "District": "NANDED",
        "State": "MAHARASHTRA",
        "Region": "Regional Office Aurangabad",
        "Division": "Nanded Division",
        "Country": "India"
    },
    {
        "Name": "Guntur B.O",
        "District": "NANDED",
        "State": "MAHARASHTRA",
        "Region": "Regional Office Aurangabad",
        "Division": "Nanded Division",
        "Country": "India"
    },
    {
        "Name": "Hatkayal",
        "District": "NANDED",
        "State": "MAHARASHTRA",
        "Region": "Regional Office Aurangabad",
        "Division": "Nanded Division",
        "Country": "India"
    },
    {
        "Name": "Kurula S.O",
        "District": "NANDED",
        "State": "MAHARASHTRA",
        "Region": "Regional Office Aurangabad",
        "Division": "Nanded Division",
        "Country": "India"
    },
    {
        "Name": "Bolka B.O",
        "District": "NANDED",
        "State": "MAHARASHTRA",
        "Region": "Regional Office Aurangabad",
        "Division": "Nanded Division",
        "Country": "India"
    },
    {
        "Name": "Nehrunagar B.O",
        "District": "NANDED",
        "State": "MAHARASHTRA",
        "Region": "Regional Office Aurangabad",
        "Division": "Nanded Division",
        "Country": "India"
    }
]