[
    {
        "Name": "Blunt Square SO",
        "District": "LUCKNOW",
        "State": "UTTAR PRADESH",
        "Region": "Lucknow  HQ Region",
        "Division": "Lucknow Division",
        "Country": "India"
    },
    {
        "Name": "R A College SO",
        "District": "LUCKNOW",
        "State": "UTTAR PRADESH",
        "Region": "Lucknow  HQ Region",
        "Division": "Lucknow Division",
        "Country": "India"
    },
    {
        "Name": "Aishbagh SO",
        "District": "LUCKNOW",
        "State": "UTTAR PRADESH",
        "Region": "Lucknow  HQ Region",
        "Division": "Lucknow Division",
        "Country": "India"
    },
    {
        "Name": "Charbagh SO",
        "District": "LUCKNOW",
        "State": "UTTAR PRADESH",
        "Region": "Lucknow  HQ Region",
        "Division": "Lucknow Division",
        "Country": "India"
    },
    {
        "Name": "Gurdwara SO",
        "District": "LUCKNOW",
        "State": "UTTAR PRADESH",
        "Region": "Lucknow  HQ Region",
        "Division": "Lucknow Division",
        "Country": "India"
    },
    {
        "Name": "Mill Road SO",
        "District": "LUCKNOW",
        "State": "UTTAR PRADESH",
        "Region": "Lucknow  HQ Region",
        "Division": "Lucknow Division",
        "Country": "India"
    },
    {
        "Name": "A N L Colony SO",
        "District": "LUCKNOW",
        "State": "UTTAR PRADESH",
        "Region": "Lucknow  HQ Region",
        "Division": "Lucknow Division",
        "Country": "India"
    },
    {
        "Name": "Arya Nagar SO",
        "District": "LUCKNOW",
        "State": "UTTAR PRADESH",
        "Region": "Lucknow  HQ Region",
        "Division": "Lucknow Division",
        "Country": "India"
    },
    {
        "Name": "Rajendranagar SO Lucknow",
        "District": "LUCKNOW",
        "State": "UTTAR PRADESH",
        "Region": "Lucknow  HQ Region",
        "Division": "Lucknow Division",
        "Country": "India"
    }
]