[
    {
        "Name": "Malakunnam BO",
        "District": "KOTTAYAM",
        "State": "KERALA",
        "Region": "Kochi Region",
        "Division": "Changanacherry Division",
        "Country": "India"
    },
    {
        "Name": "Thuruthy SO",
        "District": "KOTTAYAM",
        "State": "KERALA",
        "Region": "Kochi Region",
        "Division": "Changanacherry Division",
        "Country": "India"
    },
    {
        "Name": "Ithithanam BO",
        "District": "KOTTAYAM",
        "State": "KERALA",
        "Region": "Kochi Region",
        "Division": "Changanacherry Division",
        "Country": "India"
    }
]