[
    {
        "Name": "Jalukhera BO",
        "District": "ETAH",
        "State": "UTTAR PRADESH",
        "Region": "Agra Region",
        "Division": "Etah Division",
        "Country": "India"
    },
    {
        "Name": "Awagarh SO",
        "District": "ETAH",
        "State": "UTTAR PRADESH",
        "Region": "Agra Region",
        "Division": "Etah Division",
        "Country": "India"
    },
    {
        "Name": "Baraikalyanpur BO",
        "District": "ETAH",
        "State": "UTTAR PRADESH",
        "Region": "Agra Region",
        "Division": "Etah Division",
        "Country": "India"
    },
    {
        "Name": "Gahrana BO",
        "District": "ETAH",
        "State": "UTTAR PRADESH",
        "Region": "Agra Region",
        "Division": "Etah Division",
        "Country": "India"
    },
    {
        "Name": "Narura BO",
        "District": "ETAH",
        "State": "UTTAR PRADESH",
        "Region": "Agra Region",
        "Division": "Etah Division",
        "Country": "India"
    },
    {
        "Name": "Pondari BO",
        "District": "ETAH",
        "State": "UTTAR PRADESH",
        "Region": "Agra Region",
        "Division": "Etah Division",
        "Country": "India"
    },
    {
        "Name": "Rohina Mirjapur BO",
        "District": "ETAH",
        "State": "UTTAR PRADESH",
        "Region": "Agra Region",
        "Division": "Etah Division",
        "Country": "India"
    },
    {
        "Name": "Tikathar BO",
        "District": "ETAH",
        "State": "UTTAR PRADESH",
        "Region": "Agra Region",
        "Division": "Etah Division",
        "Country": "India"
    },
    {
        "Name": "Barabhodela BO",
        "District": "ETAH",
        "State": "UTTAR PRADESH",
        "Region": "Agra Region",
        "Division": "Etah Division",
        "Country": "India"
    },
    {
        "Name": "Basundhara BO",
        "District": "ETAH",
        "State": "UTTAR PRADESH",
        "Region": "Agra Region",
        "Division": "Etah Division",
        "Country": "India"
    },
    {
        "Name": "Khatout BO",
        "District": "ETAH",
        "State": "UTTAR PRADESH",
        "Region": "Agra Region",
        "Division": "Etah Division",
        "Country": "India"
    },
    {
        "Name": "Borakalan BO",
        "District": "ETAH",
        "State": "UTTAR PRADESH",
        "Region": "Agra Region",
        "Division": "Etah Division",
        "Country": "India"
    },
    {
        "Name": "Pipehra BO",
        "District": "ETAH",
        "State": "UTTAR PRADESH",
        "Region": "Agra Region",
        "Division": "Etah Division",
        "Country": "India"
    },
    {
        "Name": "Jarani Kalan BO",
        "District": "ETAH",
        "State": "UTTAR PRADESH",
        "Region": "Agra Region",
        "Division": "Etah Division",
        "Country": "India"
    }
]