[
    {
        "Name": "Mendra B.O",
        "District": "WASHIM",
        "State": "MAHARASHTRA",
        "Region": "Nagpur Region",
        "Division": "Akola Division",
        "Country": "India"
    },
    {
        "Name": "Mohari B.O",
        "District": "WASHIM",
        "State": "MAHARASHTRA",
        "Region": "Nagpur Region",
        "Division": "Akola Division",
        "Country": "India"
    },
    {
        "Name": "Sakhardoh B.O",
        "District": "WASHIM",
        "State": "MAHARASHTRA",
        "Region": "Nagpur Region",
        "Division": "Akola Division",
        "Country": "India"
    },
    {
        "Name": "Dhamni B.O",
        "District": "WASHIM",
        "State": "MAHARASHTRA",
        "Region": "Nagpur Region",
        "Division": "Akola Division",
        "Country": "India"
    },
    {
        "Name": "Giroli B.O",
        "District": "WASHIM",
        "State": "MAHARASHTRA",
        "Region": "Nagpur Region",
        "Division": "Akola Division",
        "Country": "India"
    },
    {
        "Name": "Hivra BK B.O",
        "District": "WASHIM",
        "State": "MAHARASHTRA",
        "Region": "Nagpur Region",
        "Division": "Akola Division",
        "Country": "India"
    },
    {
        "Name": "Kasola B.O",
        "District": "WASHIM",
        "State": "MAHARASHTRA",
        "Region": "Nagpur Region",
        "Division": "Akola Division",
        "Country": "India"
    },
    {
        "Name": "Parwa B.O",
        "District": "WASHIM",
        "State": "MAHARASHTRA",
        "Region": "Nagpur Region",
        "Division": "Akola Division",
        "Country": "India"
    },
    {
        "Name": "Poti B.O",
        "District": "WASHIM",
        "State": "MAHARASHTRA",
        "Region": "Nagpur Region",
        "Division": "Akola Division",
        "Country": "India"
    },
    {
        "Name": "Shegi B.O",
        "District": "WASHIM",
        "State": "MAHARASHTRA",
        "Region": "Nagpur Region",
        "Division": "Akola Division",
        "Country": "India"
    },
    {
        "Name": "Kothari B.O",
        "District": "WASHIM",
        "State": "MAHARASHTRA",
        "Region": "Nagpur Region",
        "Division": "Akola Division",
        "Country": "India"
    },
    {
        "Name": "Poghat B.O",
        "District": "WASHIM",
        "State": "MAHARASHTRA",
        "Region": "Nagpur Region",
        "Division": "Akola Division",
        "Country": "India"
    },
    {
        "Name": "Shendurjana B.O",
        "District": "WASHIM",
        "State": "MAHARASHTRA",
        "Region": "Nagpur Region",
        "Division": "Akola Division",
        "Country": "India"
    },
    {
        "Name": "Fulumari B.O",
        "District": "WASHIM",
        "State": "MAHARASHTRA",
        "Region": "Nagpur Region",
        "Division": "Akola Division",
        "Country": "India"
    },
    {
        "Name": "Palodi B.O",
        "District": "WASHIM",
        "State": "MAHARASHTRA",
        "Region": "Nagpur Region",
        "Division": "Akola Division",
        "Country": "India"
    },
    {
        "Name": "Dabha B.O",
        "District": "WASHIM",
        "State": "MAHARASHTRA",
        "Region": "Nagpur Region",
        "Division": "Akola Division",
        "Country": "India"
    },
    {
        "Name": "Gaiwal B.O",
        "District": "WASHIM",
        "State": "MAHARASHTRA",
        "Region": "Nagpur Region",
        "Division": "Akola Division",
        "Country": "India"
    },
    {
        "Name": "Girda B.O",
        "District": "WASHIM",
        "State": "MAHARASHTRA",
        "Region": "Nagpur Region",
        "Division": "Akola Division",
        "Country": "India"
    },
    {
        "Name": "Kawathal B.O",
        "District": "WASHIM",
        "State": "MAHARASHTRA",
        "Region": "Nagpur Region",
        "Division": "Akola Division",
        "Country": "India"
    },
    {
        "Name": "Mangrulpir S.O",
        "District": "WASHIM",
        "State": "MAHARASHTRA",
        "Region": "Nagpur Region",
        "Division": "Akola Division",
        "Country": "India"
    }
]