[
    {
        "Name": "Belawarish BO",
        "District": "AURANGABAD",
        "State": "BIHAR",
        "Region": "DivReportingCircle",
        "Division": "AurangabadBihar Division",
        "Country": "India"
    },
    {
        "Name": "Gorkatti BO",
        "District": "AURANGABAD",
        "State": "BIHAR",
        "Region": "DivReportingCircle",
        "Division": "AurangabadBihar Division",
        "Country": "India"
    },
    {
        "Name": "Munjhara BO",
        "District": "AURANGABAD",
        "State": "BIHAR",
        "Region": "DivReportingCircle",
        "Division": "AurangabadBihar Division",
        "Country": "India"
    },
    {
        "Name": "Sakardiha BO",
        "District": "AURANGABAD",
        "State": "BIHAR",
        "Region": "DivReportingCircle",
        "Division": "AurangabadBihar Division",
        "Country": "India"
    },
    {
        "Name": "Darwan BO",
        "District": "AURANGABAD",
        "State": "BIHAR",
        "Region": "DivReportingCircle",
        "Division": "AurangabadBihar Division",
        "Country": "India"
    },
    {
        "Name": "Malhad BO",
        "District": "AURANGABAD",
        "State": "BIHAR",
        "Region": "DivReportingCircle",
        "Division": "AurangabadBihar Division",
        "Country": "India"
    },
    {
        "Name": "Uphara BO",
        "District": "AURANGABAD",
        "State": "BIHAR",
        "Region": "DivReportingCircle",
        "Division": "AurangabadBihar Division",
        "Country": "India"
    },
    {
        "Name": "Budhai BO",
        "District": "AURANGABAD",
        "State": "BIHAR",
        "Region": "DivReportingCircle",
        "Division": "AurangabadBihar Division",
        "Country": "India"
    },
    {
        "Name": "Fag BO",
        "District": "AURANGABAD",
        "State": "BIHAR",
        "Region": "DivReportingCircle",
        "Division": "AurangabadBihar Division",
        "Country": "India"
    },
    {
        "Name": "Kaithi Siro BO",
        "District": "AURANGABAD",
        "State": "BIHAR",
        "Region": "DivReportingCircle",
        "Division": "AurangabadBihar Division",
        "Country": "India"
    },
    {
        "Name": "Turk Telpa BO",
        "District": "AURANGABAD",
        "State": "BIHAR",
        "Region": "DivReportingCircle",
        "Division": "AurangabadBihar Division",
        "Country": "India"
    },
    {
        "Name": "Baijalpur B.O",
        "District": "AURANGABAD",
        "State": "BIHAR",
        "Region": "DivReportingCircle",
        "Division": "AurangabadBihar Division",
        "Country": "India"
    },
    {
        "Name": "Bazar Barma B.O",
        "District": "AURANGABAD",
        "State": "BIHAR",
        "Region": "DivReportingCircle",
        "Division": "AurangabadBihar Division",
        "Country": "India"
    },
    {
        "Name": "Goh SO",
        "District": "AURANGABAD",
        "State": "BIHAR",
        "Region": "DivReportingCircle",
        "Division": "AurangabadBihar Division",
        "Country": "India"
    },
    {
        "Name": "Amari BO",
        "District": "AURANGABAD",
        "State": "BIHAR",
        "Region": "DivReportingCircle",
        "Division": "AurangabadBihar Division",
        "Country": "India"
    },
    {
        "Name": "Singhari BO",
        "District": "AURANGABAD",
        "State": "BIHAR",
        "Region": "DivReportingCircle",
        "Division": "AurangabadBihar Division",
        "Country": "India"
    },
    {
        "Name": "Tayap BO",
        "District": "AURANGABAD",
        "State": "BIHAR",
        "Region": "DivReportingCircle",
        "Division": "AurangabadBihar Division",
        "Country": "India"
    },
    {
        "Name": "Akauna BO",
        "District": "AURANGABAD",
        "State": "BIHAR",
        "Region": "DivReportingCircle",
        "Division": "AurangabadBihar Division",
        "Country": "India"
    },
    {
        "Name": "Ankuri BO",
        "District": "AURANGABAD",
        "State": "BIHAR",
        "Region": "DivReportingCircle",
        "Division": "AurangabadBihar Division",
        "Country": "India"
    },
    {
        "Name": "Darha BO",
        "District": "AURANGABAD",
        "State": "BIHAR",
        "Region": "DivReportingCircle",
        "Division": "AurangabadBihar Division",
        "Country": "India"
    },
    {
        "Name": "Gamhari BO",
        "District": "AURANGABAD",
        "State": "BIHAR",
        "Region": "DivReportingCircle",
        "Division": "AurangabadBihar Division",
        "Country": "India"
    },
    {
        "Name": "Dadpi B.O",
        "District": "AURANGABAD",
        "State": "BIHAR",
        "Region": "DivReportingCircle",
        "Division": "AurangabadBihar Division",
        "Country": "India"
    }
]