[
    {
        "Name": "Kurmidda B.O",
        "District": "RANGA REDDY",
        "State": "TELANGANA",
        "Region": "Hyderabad City Region",
        "Division": "Hyderabad South East Division",
        "Country": "India"
    },
    {
        "Name": "Manthangoud Gowrelly B.O",
        "District": "RANGA REDDY",
        "State": "TELANGANA",
        "Region": "Hyderabad City Region",
        "Division": "Hyderabad South East Division",
        "Country": "India"
    },
    {
        "Name": "Nallavelli B.O",
        "District": "RANGA REDDY",
        "State": "TELANGANA",
        "Region": "Hyderabad City Region",
        "Division": "Hyderabad South East Division",
        "Country": "India"
    },
    {
        "Name": "Nandiwanaparthi B.O",
        "District": "RANGA REDDY",
        "State": "TELANGANA",
        "Region": "Hyderabad City Region",
        "Division": "Hyderabad South East Division",
        "Country": "India"
    },
    {
        "Name": "Toolkalan B.O",
        "District": "RANGA REDDY",
        "State": "TELANGANA",
        "Region": "Hyderabad City Region",
        "Division": "Hyderabad South East Division",
        "Country": "India"
    },
    {
        "Name": "Toolkhurd B.O",
        "District": "RANGA REDDY",
        "State": "TELANGANA",
        "Region": "Hyderabad City Region",
        "Division": "Hyderabad South East Division",
        "Country": "India"
    },
    {
        "Name": "Chowderpalli B.O",
        "District": "RANGA REDDY",
        "State": "TELANGANA",
        "Region": "Hyderabad City Region",
        "Division": "Hyderabad South East Division",
        "Country": "India"
    },
    {
        "Name": "Akulamylaram B.O",
        "District": "RANGA REDDY",
        "State": "TELANGANA",
        "Region": "Hyderabad City Region",
        "Division": "Hyderabad South East Division",
        "Country": "India"
    },
    {
        "Name": "Chintapatla B.O",
        "District": "RANGA REDDY",
        "State": "TELANGANA",
        "Region": "Hyderabad City Region",
        "Division": "Hyderabad South East Division",
        "Country": "India"
    },
    {
        "Name": "Kothapalli B.O",
        "District": "RANGA REDDY",
        "State": "TELANGANA",
        "Region": "Hyderabad City Region",
        "Division": "Hyderabad South East Division",
        "Country": "India"
    },
    {
        "Name": "Mirkhanpet B.O",
        "District": "RANGA REDDY",
        "State": "TELANGANA",
        "Region": "Hyderabad City Region",
        "Division": "Hyderabad South East Division",
        "Country": "India"
    },
    {
        "Name": "Nazdeek Singaram B.O",
        "District": "RANGA REDDY",
        "State": "TELANGANA",
        "Region": "Hyderabad City Region",
        "Division": "Hyderabad South East Division",
        "Country": "India"
    },
    {
        "Name": "Medipalli B.O",
        "District": "RANGA REDDY",
        "State": "TELANGANA",
        "Region": "Hyderabad City Region",
        "Division": "Hyderabad South East Division",
        "Country": "India"
    },
    {
        "Name": "Mondigowrelly B.O",
        "District": "RANGA REDDY",
        "State": "TELANGANA",
        "Region": "Hyderabad City Region",
        "Division": "Hyderabad South East Division",
        "Country": "India"
    },
    {
        "Name": "Tatiparthy B.O",
        "District": "RANGA REDDY",
        "State": "TELANGANA",
        "Region": "Hyderabad City Region",
        "Division": "Hyderabad South East Division",
        "Country": "India"
    },
    {
        "Name": "Yacharam S.O",
        "District": "RANGA REDDY",
        "State": "TELANGANA",
        "Region": "Hyderabad City Region",
        "Division": "Hyderabad South East Division",
        "Country": "India"
    }
]